odoo/addons/web_widget_many2one_simple/README.rst
odoo/addons/web_widget_many2one_simple/__init__.py
odoo/addons/web_widget_many2one_simple/__manifest__.py
odoo/addons/web_widget_many2one_simple/demo/res_partner_view.xml
odoo/addons/web_widget_many2one_simple/i18n/de.po
odoo/addons/web_widget_many2one_simple/i18n/es.po
odoo/addons/web_widget_many2one_simple/i18n/web_widget_many2one_simple.pot
odoo/addons/web_widget_many2one_simple/readme/CONFIGURE.rst
odoo/addons/web_widget_many2one_simple/readme/CONTRIBUTORS.rst
odoo/addons/web_widget_many2one_simple/readme/DESCRIPTION.rst
odoo/addons/web_widget_many2one_simple/readme/USAGE.rst
odoo/addons/web_widget_many2one_simple/static/description/icon.png
odoo/addons/web_widget_many2one_simple/static/description/index.html
odoo/addons/web_widget_many2one_simple/static/img/preview.gif
odoo/addons/web_widget_many2one_simple/static/src/css/many2one_simple.scss
odoo/addons/web_widget_many2one_simple/static/src/js/many2one_simple_field.js
odoo/addons/web_widget_many2one_simple/static/src/xml/many2one_simple.xml
odoo_addon_web_widget_many2one_simple-15.0.1.1.0.1.dist-info/METADATA
odoo_addon_web_widget_many2one_simple-15.0.1.1.0.1.dist-info/WHEEL
odoo_addon_web_widget_many2one_simple-15.0.1.1.0.1.dist-info/top_level.txt
odoo_addon_web_widget_many2one_simple-15.0.1.1.0.1.dist-info/RECORD
